litexplore/__init__.py
litexplore/__main__.py
litexplore/app.py
litexplore/static/css/pico.min.css
litexplore/static/js/htmx.min.js
litexplore/templates/base.html
litexplore/templates/index.html
litexplore/templates/macros.html
litexplore/templates/table-rows.html
litexplore/templates/tables.html
litexplore/templates/view-table.html
litexplore-0.0.3.dist-info/METADATA
litexplore-0.0.3.dist-info/WHEEL
litexplore-0.0.3.dist-info/entry_points.txt
litexplore-0.0.3.dist-info/license_files/LICENSE
litexplore-0.0.3.dist-info/RECORD
