Metadata-Version: 2.1
Name: litexplore
Version: 0.0.3
Summary: A small example package
Project-URL: Bug Tracker, https://github.com/litements/litexplore
Project-URL: Documentation, https://github.com/litements/litexplore
Project-URL: Homepage, https://github.com/litements/litexplore
Author-email: Ricardo Ander-Egg <rsubacc@gmail.com>
Classifier: Development Status :: 3 - Alpha
Classifier: Operating System :: MacOS
Classifier: Operating System :: POSIX
Classifier: Operating System :: Unix
Classifier: Programming Language :: Python :: 3
Requires-Python: >=3.7
Requires-Dist: fastapi~=0.78
Requires-Dist: jinja2
Requires-Dist: pydantic
Requires-Dist: python-multipart
Requires-Dist: uvicorn[standard]>=0.18.2
